examples/__init__.py
examples/atari/__init__.py
examples/atari/agent.py
examples/atari/impala.py
examples/atari/local_run.py
examples/atari/network.py
examples/atari/ppo.py
examples/atari/utils.py
examples/pettingzoo/__init__.py
examples/pettingzoo/agent.py
examples/pettingzoo/impala.py
examples/pettingzoo/local_run.py
examples/pettingzoo/network.py
examples/vizdoom/__init__.py
examples/vizdoom/agent.py
examples/vizdoom/impala.py
examples/vizdoom/network.py
examples/vizdoom/utils.py
moss/__init__.py
moss/core.py
moss/types.py
moss/actor/__init__.py
moss/actor/generic.py
moss/agent/__init__.py
moss/agent/base.py
moss/buffer/__init__.py
moss/buffer/queue.py
moss/buffer/reverb.py
moss/env/__init__.py
moss/env/base.py
moss/env/envpool.py
moss/env/pettingzoo.py
moss/env/vector/__init__.py
moss/env/vector/base.py
moss/env/vector/worker.py
moss/env/wrapper/__init__.py
moss/env/wrapper/gym.py
moss/env/wrapper/pettingzoo.py
moss/learner/__init__.py
moss/learner/base.py
moss/learner/impala.py
moss/learner/ppo.py
moss/network/__init__.py
moss/network/base.py
moss/network/common.py
moss/network/ctde.py
moss/network/keys.py
moss/network/value.py
moss/network/action/__init__.py
moss/network/action/action_spec.py
moss/network/action/base.py
moss/network/action/discrete.py
moss/network/feature/__init__.py
moss/network/feature/feature.py
moss/network/feature/feature_set.py
moss/network/feature/feature_spec.py
moss/network/feature/encoder/__init__.py
moss/network/feature/encoder/common.py
moss/network/feature/encoder/image.py
moss/network/layers/__init__.py
moss/network/layers/residual_block.py
moss/network/layers/transform.py
moss/network/torso/__init__.py
moss/network/torso/dense.py
moss/network/torso/gru.py
moss/network/torso/lstm.py
moss/predictor/__init__.py
moss/predictor/base.py
moss/utils/__init__.py
moss/utils/async_utils.py
moss/utils/paths.py
moss/utils/loggers/__init__.py
moss/utils/loggers/aggregators.py
moss/utils/loggers/asynchronous.py
moss/utils/loggers/base.py
moss_rl-0.0.5.dist-info/LICENSE
moss_rl-0.0.5.dist-info/METADATA
moss_rl-0.0.5.dist-info/WHEEL
moss_rl-0.0.5.dist-info/top_level.txt
moss_rl-0.0.5.dist-info/RECORD
